image_plot/__init__.py
image_plot/example.py
image_plot/frontend/build/asset-manifest.json
image_plot/frontend/build/bootstrap.min.css
image_plot/frontend/build/index.html
image_plot/frontend/build/static/css/main.1c9bbe90.css
image_plot/frontend/build/static/css/main.1c9bbe90.css.map
image_plot/frontend/build/static/js/main.c6c2f584.js
image_plot/frontend/build/static/js/main.c6c2f584.js.LICENSE.txt
image_plot/frontend/build/static/js/main.c6c2f584.js.map
streamlit_image_plot-0.0.1.dist-info/LICENSE
streamlit_image_plot-0.0.1.dist-info/METADATA
streamlit_image_plot-0.0.1.dist-info/WHEEL
streamlit_image_plot-0.0.1.dist-info/top_level.txt
streamlit_image_plot-0.0.1.dist-info/RECORD
